multilookupdict/__init__.py
multilookupdict/multilookupdict.py
multilookupdict-0.1.7.dist-info/WHEEL
multilookupdict-0.1.7.dist-info/METADATA
multilookupdict-0.1.7.dist-info/RECORD
