Metadata-Version: 2.1
Name: multilookupdict
Version: 0.1.7
Summary: A dict-like container that allows multiple keys to address the same value.
Home-page: https://github.com/richardhadden/multilookupdict
License: MIT
Keywords: container,lookup,multi
Author: Richard Hadden
Author-email: richard.hadden@oeaw.ac.at
Requires-Python: >=3.9,<4.0
Classifier: Development Status :: 4 - Beta
Classifier: License :: OSI Approved :: MIT License
Classifier: Operating System :: OS Independent
Classifier: Programming Language :: Python :: 3
Classifier: Programming Language :: Python :: 3.10
Classifier: Programming Language :: Python :: 3.9
Classifier: Topic :: Software Development :: Libraries :: Python Modules
Project-URL: Repository, https://github.com/richardhadden/multilookupdict
